dispatch_py-0.8.0.dist-info/RECORD
dispatch_py-0.8.0.dist-info/LICENSE
dispatch_py-0.8.0.dist-info/WHEEL
dispatch_py-0.8.0.dist-info/top_level.txt
dispatch_py-0.8.0.dist-info/METADATA
dispatch/config.py
dispatch/error.py
dispatch/id.py
dispatch/fastapi.py
dispatch/flask.py
dispatch/__init__.py
dispatch/coroutine.py
dispatch/test.py
dispatch/http.py
dispatch/py.typed
dispatch/scheduler.py
dispatch/any.py
dispatch/proto.py
dispatch/function.py
dispatch/status.py
dispatch/experimental/__init__.py
dispatch/experimental/lambda_handler.py
dispatch/experimental/durable/frame311.h
dispatch/experimental/durable/registry.py
dispatch/experimental/durable/frame312.h
dispatch/experimental/durable/__init__.py
dispatch/experimental/durable/frame308.h
dispatch/experimental/durable/frame.pyi
dispatch/experimental/durable/README.md
dispatch/experimental/durable/frame.cpython-311-darwin.so
dispatch/experimental/durable/frame313.h
dispatch/experimental/durable/frame309.h
dispatch/experimental/durable/py.typed
dispatch/experimental/durable/frame.c
dispatch/experimental/durable/frame310.h
dispatch/experimental/durable/function.py
dispatch/signature/digest.py
dispatch/signature/key.py
dispatch/signature/request.py
dispatch/signature/__init__.py
dispatch/integrations/httpx.py
dispatch/integrations/__init__.py
dispatch/integrations/openai.py
dispatch/integrations/http.py
dispatch/integrations/py.typed
dispatch/integrations/requests.py
dispatch/integrations/slack.py
dispatch/sdk/__init__.py
dispatch/sdk/v1/status_pb2.py
dispatch/sdk/v1/poll_pb2.pyi
dispatch/sdk/v1/poll_pb2.py
dispatch/sdk/v1/status_pb2.pyi
dispatch/sdk/v1/exit_pb2.pyi
dispatch/sdk/v1/function_pb2.pyi
dispatch/sdk/v1/function_pb2.py
dispatch/sdk/v1/__init__.py
dispatch/sdk/v1/dispatch_pb2.pyi
dispatch/sdk/v1/exit_pb2.py
dispatch/sdk/v1/dispatch_pb2.py
dispatch/sdk/v1/error_pb2.pyi
dispatch/sdk/v1/py.typed
dispatch/sdk/v1/call_pb2.pyi
dispatch/sdk/v1/error_pb2.py
dispatch/sdk/v1/call_pb2.py
dispatch/sdk/python/__init__.py
dispatch/sdk/python/v1/__init__.py
dispatch/sdk/python/v1/pickled_pb2.py
dispatch/sdk/python/v1/pickled_pb2.pyi
