Metadata-Version: 2.1
Name: dispatch-py
Version: 0.8.0
Summary: Develop reliable distributed systems with Dispatch.
Requires-Python: >=3.8
License-File: LICENSE
Requires-Dist: aiohttp >=3.9.4
Requires-Dist: protobuf >=4.24.0
Requires-Dist: types-protobuf >=4.24.0.20240129
Requires-Dist: http-message-signatures >=0.5.0
Requires-Dist: tblib >=3.0.0
Requires-Dist: typing-extensions >=4.10
Provides-Extra: dev
Requires-Dist: httpx >=0.27.0 ; extra == 'dev'
Requires-Dist: black >=24.1.0 ; extra == 'dev'
Requires-Dist: isort >=5.13.2 ; extra == 'dev'
Requires-Dist: mypy >=1.10.0 ; extra == 'dev'
Requires-Dist: pytest >=8.0.0 ; extra == 'dev'
Requires-Dist: pytest-asyncio >=0.23.7 ; extra == 'dev'
Requires-Dist: fastapi >=0.109.0 ; extra == 'dev'
Requires-Dist: coverage >=7.4.1 ; extra == 'dev'
Requires-Dist: requests >=2.31.0 ; extra == 'dev'
Requires-Dist: types-requests >=2.31.0.20240125 ; extra == 'dev'
Requires-Dist: uvicorn >=0.28.0 ; extra == 'dev'
Requires-Dist: types-Flask >=1.1.6 ; extra == 'dev'
Requires-Dist: flask >=3 ; extra == 'dev'
Requires-Dist: awslambdaric-stubs ; extra == 'dev'
Provides-Extra: docs
Requires-Dist: mkdocs ==1.5.3 ; extra == 'docs'
Requires-Dist: mkdocstrings[python] ==0.24.0 ; extra == 'docs'
Requires-Dist: mkdocs-material ==9.5.9 ; extra == 'docs'
Requires-Dist: mkdocs-gen-files ==0.5.0 ; extra == 'docs'
Requires-Dist: mkdocs-literate-nav ==0.6.1 ; extra == 'docs'
Requires-Dist: mike ==2.0.0 ; extra == 'docs'
Provides-Extra: fastapi
Requires-Dist: fastapi ; extra == 'fastapi'
Provides-Extra: flask
Requires-Dist: flask ; extra == 'flask'
Provides-Extra: httpx
Requires-Dist: httpx ; extra == 'httpx'
Provides-Extra: lambda
Requires-Dist: awslambdaric ; extra == 'lambda'
